sepordeh/__init__.py
sepordeh/payment.py
sepordeh-0.0.1.dist-info/LICENSE
sepordeh-0.0.1.dist-info/METADATA
sepordeh-0.0.1.dist-info/WHEEL
sepordeh-0.0.1.dist-info/top_level.txt
sepordeh-0.0.1.dist-info/RECORD
