Metadata-Version: 2.1
Name: sepordeh
Version: 0.0.1
Summary: using www.sepordeh.com webservice
Home-page: https://github.com/sepordeh/sepordeh-python.git
Author: sepordeh
Author-email: info@sepordeh.com
Project-URL: Bug Tracker, https://github.com/sepordeh/sepordeh-python/issues
Classifier: Programming Language :: Python :: 3
Classifier: License :: OSI Approved :: MIT License
Classifier: Operating System :: OS Independent
Requires-Python: >=3.7
License-File: LICENSE
Requires-Dist: requests
Requires-Dist: certifi
Requires-Dist: charset-normalizer
Requires-Dist: idna
Requires-Dist: urllib3
